{
    "Id": 66,
    "Title": "دُعَاءُ الرِّيحِ",
    "Scrollable": false,
    "Content": [
        {
            "Zekr": "اللَّهُمَّ إِنِّي أَسْأَلُكَ خَيْرَهَا، وَأَعُوذُ بِكَ مِنْ شَرِّهَا",
            "Source": "أخرجه أبو داود، 4/ 326، برقم 5099، وابن ماجه، 2/ 1228، برقم 3727، وانظر: صحيح ابن ماجه، 2/ 305.",
            "Count": "1"
        },
        {
            "Zekr": "اللَّهُمَّ إِنِّي أَسْأَلُكَ خَيْرَهَا، وَخَيْرَ مَا فِيهَا، وَخَيْرَ مَا أُرْسِلَتْ بِهِ، وَأَعُوذُ بِكَ مِنْ شَرِّهَا، وَشَرِّ مَا فِيهَا، وَشَرِّ مَا أُرْسِلَتْ بِهِ",
            "Source": "مسلم، واللفظ له، 2/ 666، برقم 899، والبخاري، 4/ 76 برقم 3206، ورقم 4829.",
            "Count": "1"
        }
    ]
}